jinjafy.py
jinjafy-0.1.0.dist-info/DESCRIPTION.rst
jinjafy-0.1.0.dist-info/METADATA
jinjafy-0.1.0.dist-info/RECORD
jinjafy-0.1.0.dist-info/WHEEL
jinjafy-0.1.0.dist-info/entry_points.txt
jinjafy-0.1.0.dist-info/metadata.json
jinjafy-0.1.0.dist-info/pbr.json
jinjafy-0.1.0.dist-info/top_level.txt
