Metadata-Version: 2.0
Name: jinjafy
Version: 0.1.0
Summary: Render a Jinja2 template from the commandline, writing it to stdout
Home-page: https://github.com/mshenfield/jinjafy
Author: Max Shenfield
Author-email: shenfieldmax@gmail.com
License: MIT
Keywords: jinja2,cli
Platform: UNKNOWN
Classifier: Development Status :: 3 - Alpha
Classifier: Environment :: Console
Classifier: Intended Audience :: Developers
Classifier: License :: OSI Approved :: MIT License
Classifier: Natural Language :: English
Classifier: Operating System :: OS Independent
Classifier: Programming Language :: Python :: 3
Classifier: Programming Language :: Python :: 3.6
Classifier: Topic :: Utilities
Requires-Dist: jinja2 (~=2.0)
Provides-Extra: test
Requires-Dist: pytest (~=3.0); extra == 'test'
